{
  "serviceid": 3,
  "servicename": "djl服务1",
  "requestTemplate": "{\n  \"string\": \"我是string\",\n  \"bool\": true,\n  \"int\": 1111111111111,\n  \"number\": 1.22,\n  \"object\": {\n    \"string\": \"我是string\",\n    \"bool\": true,\n    \"int\": 1,\n    \"number\": 1.22,\n    \"object\": {\n      \"string\": \"我是string\",\n      \"bool\": true,\n      \"int\": 1,\n      \"number\": 1.22\n    }\n  },\n  \"list\": [\n    {\n      \"string\": \"我是string\",\n      \"bool\": true,\n      \"int\": 1,\n      \"number\": 1.22\n    },\n    {\n      \"string\": \"我是string\",\n      \"bool\": true,\n      \"int\": 1,\n      \"number\": 1.22\n    }\n  ]\n}\n",
  "responceTemplate": "{\n  \"string\": \"我是string\",\n  \"bool\": true,\n  \"int\": 1111111111111,\n  \"number\": 1.22,\n  \"object\": {\n    \"string\": \"我是string\",\n    \"bool\": true,\n    \"int\": 1,\n    \"number\": 1.22,\n    \"object\": {\n      \"string\": \"我是string\",\n      \"bool\": true,\n      \"int\": 1,\n      \"number\": 1.22\n    }\n  },\n  \"list\": [\n    {\n      \"string\": \"我是string\",\n      \"bool\": true,\n      \"int\": 1,\n      \"number\": 1.22\n    },\n    {\n      \"string\": \"我是string\",\n      \"bool\": true,\n      \"int\": 1,\n      \"number\": 1.22\n    }\n  ]\n}\n",
  "$$hashKey": "object:448",
  "$$isChecked": true
}
